basicgym/__init__.py
basicgym/types.py
basicgym/utils.py
basicgym/version.py
basicgym/envs/__init__.py
basicgym/envs/synthetic.py
basicgym/envs/simulator/__init__.py
basicgym/envs/simulator/base.py
basicgym/envs/simulator/function.py
recgym/__init__.py
recgym/types.py
recgym/utils.py
recgym/version.py
recgym/envs/__init__.py
recgym/envs/rec.py
recgym/envs/simulator/__init__.py
recgym/envs/simulator/base.py
recgym/envs/simulator/function.py
rtbgym/__init__.py
rtbgym/types.py
rtbgym/utils.py
rtbgym/version.py
rtbgym/envs/__init__.py
rtbgym/envs/rtb.py
rtbgym/envs/wrapper_rtb.py
rtbgym/envs/simulator/__init__.py
rtbgym/envs/simulator/base.py
rtbgym/envs/simulator/bidder.py
rtbgym/envs/simulator/function.py
rtbgym/envs/simulator/rtb_synthetic.py
scope_rl/__init__.py
scope_rl/types.py
scope_rl/utils.py
scope_rl/version.py
scope_rl/dataset/__init__.py
scope_rl/dataset/base.py
scope_rl/dataset/synthetic.py
scope_rl/ope/__init__.py
scope_rl/ope/estimators_base.py
scope_rl/ope/input.py
scope_rl/ope/online.py
scope_rl/ope/ope.py
scope_rl/ope/ops.py
scope_rl/ope/continuous/__init__.py
scope_rl/ope/continuous/basic_estimators.py
scope_rl/ope/continuous/cumulative_distribution_estimators.py
scope_rl/ope/continuous/marginal_estimators.py
scope_rl/ope/discrete/__init__.py
scope_rl/ope/discrete/basic_estimators.py
scope_rl/ope/discrete/cumulative_distribution_estimators.py
scope_rl/ope/discrete/marginal_estimators.py
scope_rl/ope/weight_value_learning/__init__.py
scope_rl/ope/weight_value_learning/augmented_lagrangian_learning_continuous.py
scope_rl/ope/weight_value_learning/augmented_lagrangian_learning_discrete.py
scope_rl/ope/weight_value_learning/base.py
scope_rl/ope/weight_value_learning/function.py
scope_rl/ope/weight_value_learning/minimax_value_learning_continuous.py
scope_rl/ope/weight_value_learning/minimax_value_learning_discrete.py
scope_rl/ope/weight_value_learning/minimax_weight_learning_continuous.py
scope_rl-0.2.1.dist-info/LICENSE
scope_rl-0.2.1.dist-info/METADATA
scope_rl-0.2.1.dist-info/WHEEL
scope_rl-0.2.1.dist-info/top_level.txt
scope_rl-0.2.1.dist-info/RECORD
