Metadata-Version: 2.1
Name: scope-rl
Version: 0.2.1
Summary: SCOPE-RL: A pipeline for offline reinforcement learning research and applications
Home-page: https://github.com/hakuhodo-technologies/scope-rl
Author: Haruka Kiyohara
Author-email: hk844@cornell.edu
License: Apache License 2.0
Keywords: off-policy evaluation,offline reinforcement learning,risk assessment
Platform: UNKNOWN
Classifier: Intended Audience :: Science/Research
Classifier: Programming Language :: Python :: 3.9
Classifier: Programming Language :: Python :: 3.10
Classifier: Programming Language :: Python :: 3.11
Classifier: Topic :: Scientific/Engineering
Classifier: Topic :: Scientific/Engineering :: Mathematics
Classifier: Topic :: Scientific/Engineering :: Artificial Intelligence
Classifier: Topic :: Software Development
Classifier: Topic :: Software Development :: Libraries
Classifier: Topic :: Software Development :: Libraries :: Python Modules
Classifier: License :: OSI Approved :: Apache Software License
License-File: LICENSE
Requires-Dist: scipy (>=1.10.1)
Requires-Dist: numpy (>=1.22.4)
Requires-Dist: pandas (>=1.5.3)
Requires-Dist: scikit-learn (>=1.0.2)
Requires-Dist: matplotlib (>=3.7.1)
Requires-Dist: seaborn (>=0.11.2)
Requires-Dist: torch (>=2.0.0)
Requires-Dist: pytorch-revgrad (==0.2.0)
Requires-Dist: d3rlpy (>=2.0.2)
Requires-Dist: gym (>=0.26.2)
Requires-Dist: gymnasium (>=0.28.1)
Requires-Dist: hydra-core (>=1.3.2)
